domestic_violence_news_classifer_spanish/.DS_Store
domestic_violence_news_classifer_spanish/__init__.py
domestic_violence_news_classifer_spanish/domestic_violence_classifier.py
domestic_violence_news_classifer_spanish/test_domestic_violence_classifier.py
domestic_violence_news_classifer_spanish/__pycache__/cleaner.cpython-37.pyc
domestic_violence_news_classifer_spanish/__pycache__/sentiment_analysis.cpython-37.pyc
domestic_violence_news_classifer_spanish/saved_model/.DS_Store
domestic_violence_news_classifer_spanish/saved_model/model.h5
domestic_violence_news_classifer_spanish/saved_model/model.json
domestic_violence_news_classifer_spanish/saved_model/tokenizer.pickle
domestic_violence_news_classifer_spanish-0.0.4.dist-info/LICENSE
domestic_violence_news_classifer_spanish-0.0.4.dist-info/METADATA
domestic_violence_news_classifer_spanish-0.0.4.dist-info/WHEEL
domestic_violence_news_classifer_spanish-0.0.4.dist-info/top_level.txt
domestic_violence_news_classifer_spanish-0.0.4.dist-info/RECORD
